{"_id":"3811342","rating":{"average":"6.5","rating_people":"19410","stars":["6.4","26.9","55.0","10.1","1.6"]},"genres":["剧情","动作","犯罪"],"season_count":"","pubdate":["2009-08-13"],"title":"Laughing Gor之变节 Laughing Gor之變節","lens_id":144390,"poster":"https://img3.doubanio.com/view/movie_poster_cover/lpst/public/p1359679594.jpg","countries":["香港"],"site":"b.tvb.com/laughing/","summary":"Laughing（谢天华饰）本认是警方的卧底，但政因为一择宗贩毒案件，被警司潘SIR（黄日华饰）追捕。\n其实Laughing加入警队之前，本就是个黑帮成员，一直跟随其老大一哥（黄秋生饰）在道上打拼。一哥对Laughing照顾有加，Laughing视一哥有如亲兄。一哥为了保护自己的地盘及非法生意，竟要求Laughing投考警队，让他可以掌握警方行动。\nLaughing在警校成绩优异，可惜天意弄人，他根本没机会待在警队，因为反黑警司冼SIR（元彪饰）被Laughing的黑道气味所吸引，竟指派他做卧底探员。就这样，Laughing竟成了\"双重卧底\"，一哥也乐得Laughing被送进社团去对付自己的同门座头（吴镇宇饰）。在这已经复杂的状况下，一件事情令Laughing的处境更复杂，他竟爱上了座头的妹妹Karen（陈法拉饰）。\n面对法治、恩义、感情...","languages":["粤语"],"directors":[{"name":"邱礼涛","id":"1274313"}],"writers":[{"name":"叶天成","id":"search"},{"name":"潘漫红","id":"search"},{"name":"黄洋达","id":"search"}],"douban_site":"","year":"2009","duration":"89","imdb":"tt1483421","aka":["无间风云","Laughing哥前传","Turning Point"],"episodes":"","casts":[{"name":"谢天华","id":"1010833"},{"name":"黄秋生","id":"1050076"},{"name":"吴镇宇","id":"1037098"},{"name":"陈法拉","id":"1033379"},{"name":"黄日华","id":"1050735"},{"name":"元彪","id":"1163752"},{"name":"曾志伟","id":"1002862"},{"name":"黎耀祥","id":"1274440"},{"name":"黄德斌","id":"1274442"},{"name":"陈键锋","id":"1047528"},{"name":"吕慧仪","id":"1314568"}]}
